wuggy/__init__.py
wuggy/evaluators/__init__.py
wuggy/evaluators/ld1nn.py
wuggy/generators/__init__.py
wuggy/generators/wuggygenerator.py
wuggy/plugins/__init__.py
wuggy/plugins/baselanguageplugin.py
wuggy/utilities/__init__.py
wuggy/utilities/bigramchain.py
wuggy-1.1.2.dist-info/LICENSE
wuggy-1.1.2.dist-info/METADATA
wuggy-1.1.2.dist-info/WHEEL
wuggy-1.1.2.dist-info/top_level.txt
wuggy-1.1.2.dist-info/RECORD
