Metadata-Version: 2.1
Name: wuggy
Version: 1.1.2
Summary: Wuggy: A multilingual pseudoword generator
Home-page: https://github.com/WuggyCode/wuggy
Author: Emmanuel Keuleers
Author-email: E.A.Keuleers@tilburguniversity.edu
Classifier: Programming Language :: Python :: 3
Classifier: License :: OSI Approved :: MIT License
Classifier: Operating System :: OS Independent
Requires-Python: >=3.8
License-File: LICENSE
Requires-Dist: Levenshtein >=0.12.0
Requires-Dist: statsmodels >=0.12.1
